.coveragerc
AUTHORS
ChangeLog
LICENSE
MANIFEST.in
README.rst
requirements.txt
setup.cfg
setup.py
test-requirements.txt
tox.ini
bin/github2gitlab
github2gitlab/__init__.py
github2gitlab/main.py
github2gitlab.egg-info/PKG-INFO
github2gitlab.egg-info/SOURCES.txt
github2gitlab.egg-info/dependency_links.txt
github2gitlab.egg-info/pbr.json
github2gitlab.egg-info/requires.txt
github2gitlab.egg-info/top_level.txt
tests/integration.py
tests/test_github2gitlab.py