Metadata-Version: 1.1
Name: github2gitlab
Version: 1.4.0
Summary: command line tool to migrate projects from GitHub to GitLab
Home-page: http://workbench.dachary.org/dachary/github2gitlab
Author: Loic Dachary
Author-email: loic@dachary.org
License: UNKNOWN
Platform: UNKNOWN
Classifier: Environment :: No Input/Output (Daemon)
Classifier: Intended Audience :: Information Technology
Classifier: Intended Audience :: System Administrators
Classifier: Operating System :: POSIX :: Linux
Classifier: License :: OSI Approved :: GNU Affero General Public License v3 or later (AGPLv3+)
Classifier: Programming Language :: Python
Classifier: Programming Language :: Python :: 2.7
Classifier: Topic :: Utilities
